run_by_arch/__init__.py
run_by_arch-0.0.1.dist-info/LICENSE
run_by_arch-0.0.1.dist-info/METADATA
run_by_arch-0.0.1.dist-info/WHEEL
run_by_arch-0.0.1.dist-info/entry_points.txt
run_by_arch-0.0.1.dist-info/top_level.txt
run_by_arch-0.0.1.dist-info/RECORD
