Metadata-Version: 2.1
Name: run-by-arch
Version: 0.0.1
Summary: Run different shell commands depending on your OS or CPU arch.
Home-page: https://github.com/neocrym/run-by-arch
Author: Neocrym Records Inc.
Author-email: engineering@neocrym.com
License: MIT
Platform: UNKNOWN
Classifier: Environment :: Console
Classifier: Intended Audience :: Developers
Classifier: Operating System :: POSIX :: Linux
Classifier: Operating System :: MacOS :: MacOS X
Classifier: Operating System :: Microsoft :: Windows
Classifier: Programming Language :: Python :: 2.6
Classifier: Programming Language :: Python :: 2.7
Classifier: Programming Language :: Python :: 3.3
Classifier: Programming Language :: Python :: 3.4
Classifier: Programming Language :: Python :: 3.5
Classifier: Programming Language :: Python :: 3.6
